pyswag/__init__.py
pyswag/__main__.py
pyswag-0.0.3.dist-info/LICENSE
pyswag-0.0.3.dist-info/METADATA
pyswag-0.0.3.dist-info/WHEEL
pyswag-0.0.3.dist-info/dependency_links.txt
pyswag-0.0.3.dist-info/entry_points.txt
pyswag-0.0.3.dist-info/top_level.txt
pyswag-0.0.3.dist-info/RECORD
